hume.py
humeconfig.py
humed.py
humetools.py
humed-1.2.28.dist-info/DESCRIPTION.rst
humed-1.2.28.dist-info/METADATA
humed-1.2.28.dist-info/RECORD
humed-1.2.28.dist-info/WHEEL
humed-1.2.28.dist-info/entry_points.txt
humed-1.2.28.dist-info/metadata.json
humed-1.2.28.dist-info/namespace_packages.txt
humed-1.2.28.dist-info/top_level.txt
