Metadata-Version: 2.0
Name: humed
Version: 1.2.28
Summary: Agnostic sysadmin/devops instrumentation tool. Includes hume and humed.
Home-page: https://github.com/buanzo/hume
Author: Arturo "Buanzo" Busleiman
Author-email: buanzo@buanzo.com.ar
License: MIT License
Keywords: hume,humed,nagios,logstash,slack,syslog,kant,fluentd,devops,sysadmin,agnostic,prometheus
Platform: UNKNOWN
Classifier: Environment :: Console
Classifier: Intended Audience :: Developers
Classifier: License :: OSI Approved :: MIT License
Classifier: Programming Language :: Python
Classifier: Programming Language :: Python :: 3.6
Classifier: Programming Language :: Python :: 3.7
Classifier: Programming Language :: Python :: 3.8
Classifier: Programming Language :: Python :: Implementation :: PyPy
Requires-Python: >=3.6
Requires-Dist: pid (==3.0.3)
Requires-Dist: psutil (==5.7.0)
Requires-Dist: requests (>=2.20.0)
Requires-Dist: python-logstash-async (==1.6.4)
Requires-Dist: confuse (==1.1.0)
Requires-Dist: pyzmq (==19.0.1)
Requires-Dist: webhook-listener (>=0.0.3)
Requires-Dist: Jinja2 (>=2.10.1)
